chain_composer/__init__.py
chain_composer/_core_internal/__init__.py
chain_composer/_core_internal/_chain_builder.py
chain_composer/_core_internal/_chain_manager.py
chain_composer/_core_internal/_chain_wrapper.py
chain_composer/_error_handling/__init__.py
chain_composer/_error_handling/classes/__init__.py
chain_composer/_error_handling/classes/_base_chain_error.py
chain_composer/_error_handling/classes/_llm_json_decode_error.py
chain_composer/_error_handling/classes/_llm_validation_error.py
chain_composer/_error_handling/enums/__init__.py
chain_composer/_error_handling/enums/_error_reference.py
chain_composer/_error_handling/enums/_error_types.py
chain_composer/_error_handling/factories/__init__.py
chain_composer/_error_handling/factories/exception_factory.py
chain_composer/_error_handling/messages/__init__.py
chain_composer/_error_handling/messages/_chain_builder_error_messages.py
chain_composer/_error_handling/messages/_chain_composer_error_messages.py
chain_composer/_error_handling/messages/_chain_manager_error_messages.py
chain_composer/_error_handling/messages/_chain_wrapper_error_messages.py
chain_composer/_error_handling/messages/_universal_error_messages.py
chain_composer/_error_handling/registry/__init__.py
chain_composer/_error_handling/registry/_error_registry.py
chain_composer/_error_handling/utils/__init__.py
chain_composer/_error_handling/utils/_error_message_map.py
chain_composer/_error_handling/utils/_error_type_finder.py
chain_composer/_error_handling/validators/__init__.py
chain_composer/_error_handling/validators/_chain_composer_validator.py
chain_composer/_logging/__init__.py
chain_composer/_logging/log_helpers.py
chain_composer/_type_aliases/__init__.py
chain_composer/_type_aliases/type_aliases.py
chain_composer/core/__init__.py
chain_composer/core/chain_composer.py
chain_composer/types/__init__.py
chain_composer/types/dataclasses/__init__.py
chain_composer/types/dataclasses/validation_result.py
chain_composer/utils/__init__.py
ChainComposer-0.1.8.dist-info/METADATA
ChainComposer-0.1.8.dist-info/WHEEL
ChainComposer-0.1.8.dist-info/top_level.txt
ChainComposer-0.1.8.dist-info/RECORD
