Metadata-Version: 2.1
Name: ChainComposer
Version: 0.1.8
Summary: A tool to quickly and easily build complex LLM chains. Chain Composer is a sophisticated wrapper around core LangChain functionality allowing for quickly building complex multi-layer LLM chains.
Author-email: Spencer Presley <spencerpresley96@gmail.com>
Project-URL: Homepage, https://github.com/SpencerPresley/AIChainComposer
Project-URL: Bug Tracker, https://github.com/SpencerPresley/AIChainComposer/issues
Project-URL: PyPI, https://pypi.org/project/ChainComposer/
Classifier: Programming Language :: Python :: 3
Classifier: License :: OSI Approved :: MIT License
Classifier: Operating System :: OS Independent
Requires-Python: <4.0,>=3.9
Requires-Dist: langchain==0.3.7
Requires-Dist: langchain-anthropic==0.3.0
Requires-Dist: langchain-core==0.3.19
Requires-Dist: langchain-google-genai==2.0.5
Requires-Dist: langchain-openai==0.2.9
Requires-Dist: openai==1.58.1
Requires-Dist: pydantic==2.9.2
Requires-Dist: platformdirs==4.3.6
Provides-Extra: test
Requires-Dist: pytest>=7.4.3; extra == "test"
Requires-Dist: pytest-cov>=6.0.0; extra == "test"
Requires-Dist: pytest-mock>=3.12.0; extra == "test"
Requires-Dist: pytest-asyncio>=0.21.1; extra == "test"
Requires-Dist: python-dotenv>=1.0.0; extra == "test"
Provides-Extra: dev
Requires-Dist: black>=23.11.0; extra == "dev"
Requires-Dist: mypy>=1.7.0; extra == "dev"
Requires-Dist: isort>=5.12.0; extra == "dev"
Requires-Dist: flake8>=6.1.0; extra == "dev"
Provides-Extra: docs
Requires-Dist: sphinx; extra == "docs"
Requires-Dist: piccolo-theme; extra == "docs"
Requires-Dist: sphinx-autodoc-typehints; extra == "docs"
Requires-Dist: pydata-sphinx-theme; extra == "docs"
